cheetahpy/VERSION
cheetahpy/__init__.py
cheetahpy/cheetahpy.py
cheetahpy/local_opendata.py
cheetahpy-0.5.2.dist-info/LICENSE
cheetahpy-0.5.2.dist-info/METADATA
cheetahpy-0.5.2.dist-info/WHEEL
cheetahpy-0.5.2.dist-info/top_level.txt
cheetahpy-0.5.2.dist-info/RECORD
