Metadata-Version: 2.1
Name: cheetahpy
Version: 0.5.2
Summary: Python API for accessing Golden Cheetah
Author-email: Ryan Duecker <ryan.duecker@yahoo.com>
License: MIT License
Classifier: Programming Language :: Python :: 3
Classifier: License :: OSI Approved :: MIT License
Classifier: Operating System :: OS Independent
Requires-Python: >=3.8
License-File: LICENSE
Requires-Dist: pandas
Requires-Dist: requests
Provides-Extra: dev
Requires-Dist: pytest ; extra == 'dev'
Requires-Dist: flake8 ; extra == 'dev'
Requires-Dist: pylint ; extra == 'dev'
Provides-Extra: linting
Requires-Dist: flake8 ; extra == 'linting'
Requires-Dist: pylint ; extra == 'linting'
Provides-Extra: testing
Requires-Dist: pytest ; extra == 'testing'
